block/__init__.py
block/block.py
block-0.0.2.dist-info/DESCRIPTION.rst
block-0.0.2.dist-info/METADATA
block-0.0.2.dist-info/RECORD
block-0.0.2.dist-info/WHEEL
block-0.0.2.dist-info/metadata.json
block-0.0.2.dist-info/top_level.txt
