Metadata-Version: 2.0
Name: block
Version: 0.0.2
Summary: Improved block matrix creation for numpy and PyTorch.
Home-page: https://github.com/bamos/block
Author: Brandon Amos
Author-email: bamos@cs.cmu.edu
License: Apache 2.0
Platform: any
Requires-Dist: numpy (>=1<2)
